README.md
setup.cfg
setup.py
transpo/__init__.py
transpo/main.py
transpo_dir.egg-info/PKG-INFO
transpo_dir.egg-info/SOURCES.txt
transpo_dir.egg-info/dependency_links.txt
transpo_dir.egg-info/entry_points.txt
transpo_dir.egg-info/top_level.txt