Metadata-Version: 2.1
Name: transpo-dir
Version: 0.2.1
Summary: Transpose the directory structure.
Home-page: https://github.com/tos-kamiya/transpo
Author: Toshihiro Kamiya
Author-email: kamiya@mbj.nifty.com
License: BSD 2-Clause License
Platform: UNKNOWN
Classifier: Programming Language :: Python :: 3.8
Classifier: Programming Language :: Python :: 3.9
Classifier: Programming Language :: Python :: 3.10
Classifier: License :: OSI Approved :: BSD License
Classifier: Operating System :: MacOS :: MacOS X
Classifier: Operating System :: POSIX :: Linux
Requires-Python: >=3.8
